fiasto_py-0.1.4.dist-info/METADATA
fiasto_py-0.1.4.dist-info/WHEEL
fiasto_py-0.1.4.dist-info/license_files/LICENSE
fiasto_py/__init__.py
fiasto_py/fiasto_py.cpython-313-darwin.so
fiasto_py-0.1.4.dist-info/RECORD
