Metadata-Version: 2.1
Name: fiasto-py
Version: 0.1.4
Classifier: Development Status :: 4 - Beta
Classifier: Intended Audience :: Science/Research
Classifier: Intended Audience :: Developers
Classifier: License :: OSI Approved :: MIT License
Classifier: Operating System :: OS Independent
Classifier: Programming Language :: Python :: 3
Classifier: Programming Language :: Python :: 3.8
Classifier: Programming Language :: Python :: 3.9
Classifier: Programming Language :: Python :: 3.10
Classifier: Programming Language :: Python :: 3.11
Classifier: Programming Language :: Python :: 3.12
Classifier: Programming Language :: Python :: 3.13
Classifier: Programming Language :: Rust
Classifier: Topic :: Scientific/Engineering :: Mathematics
Classifier: Topic :: Scientific/Engineering :: Information Analysis
Classifier: Topic :: Software Development :: Libraries :: Python Modules
License-File: LICENSE
Summary: Python bindings for fiasto - A language-agnostic modern Wilkinson's formula parser and lexer
Keywords: formula,parser,statistics,mixed-effects,wilkinson,rust,pyo3
Author-email: Alex Hallam <alex@example.com>
Maintainer-email: Alex Hallam <alex@example.com>
License: MIT
Requires-Python: >=3.8
Project-URL: Homepage, https://github.com/alexhallam/fiasto-py
Project-URL: Repository, https://github.com/alexhallam/fiasto-py
Project-URL: Documentation, https://github.com/alexhallam/fiasto-py#readme
Project-URL: Bug Tracker, https://github.com/alexhallam/fiasto-py/issues
Project-URL: Changelog, https://github.com/alexhallam/fiasto-py/blob/main/CHANGELOG.md
